pyproject_validate/__init__.py
pyproject_validate/__main__.py
pyproject_validate/_version.py
pyproject_validate/cli.py
pyproject_validate/handlers.py
pyproject_validate/models.py
pyproject_validate/utils.py
pyproject_validate/validators.py
pyproject_validate-0.1.0.dist-info/METADATA
pyproject_validate-0.1.0.dist-info/WHEEL
pyproject_validate-0.1.0.dist-info/entry_points.txt
pyproject_validate-0.1.0.dist-info/license_files/LICENSE.txt
pyproject_validate-0.1.0.dist-info/RECORD
