Metadata-Version: 2.1
Name: pyproject-validate
Version: 0.1.0
Summary: Validate and format pyproject.toml files
Project-URL: Documentation, https://github.com/ofek/pyproject-validate#readme
Project-URL: Issues, https://github.com/ofek/pyproject-validate/issues
Project-URL: Source, https://github.com/ofek/pyproject-validate
Author-email: Ofek Lev <oss@ofek.dev>
Classifier: Development Status :: 4 - Beta
Classifier: Programming Language :: Python
Classifier: Programming Language :: Python :: 3.10
Classifier: Programming Language :: Python :: 3.7
Classifier: Programming Language :: Python :: 3.8
Classifier: Programming Language :: Python :: 3.9
Classifier: Programming Language :: Python :: Implementation :: CPython
Classifier: Programming Language :: Python :: Implementation :: PyPy
Requires-Python: >=3.7
Requires-Dist: packaging
Requires-Dist: pydantic
Requires-Dist: tomli
Requires-Dist: tomli-w
